pyetm/__init__.py
pyetm/exceptions.py
pyetm/logger.py
pyetm/optional.py
pyetm/types.py
pyetm/client/__init__.py
pyetm/client/account.py
pyetm/client/client.py
pyetm/client/curves.py
pyetm/client/customcurves.py
pyetm/client/gqueries.py
pyetm/client/meritorder.py
pyetm/client/parameters.py
pyetm/client/scenario.py
pyetm/client/session.py
pyetm/client/utils.py
pyetm/data/G2A_parameters.csv
pyetm/data/house_properties.csv
pyetm/data/thermostat_values.csv
pyetm/myc/__init__.py
pyetm/myc/model.py
pyetm/myc/pool.py
pyetm/profiles/__init__.py
pyetm/profiles/cfactors.py
pyetm/profiles/heat/__init__.py
pyetm/profiles/heat/buildings.py
pyetm/profiles/heat/cooling.py
pyetm/profiles/heat/households.py
pyetm/profiles/heat/smoothing.py
pyetm/sessions/__init__.py
pyetm/sessions/abc.py
pyetm/sessions/aiohttp.py
pyetm/sessions/requests.py
pyetm/utils/__init__.py
pyetm/utils/categorisation.py
pyetm/utils/converter.py
pyetm/utils/excel.py
pyetm/utils/general.py
pyetm/utils/interpolation.py
pyetm/utils/lookup.py
pyetm/utils/loop.py
pyetm/utils/profiles.py
pyetm/utils/regionalisation.py
pyetm/utils/url.py
pyetm-1.4.5.dist-info/licenses/LICENSE
pyetm-1.4.5.dist-info/METADATA
pyetm-1.4.5.dist-info/WHEEL
pyetm-1.4.5.dist-info/top_level.txt
pyetm-1.4.5.dist-info/RECORD
