Metadata-Version: 2.4
Name: pyetm
Version: 1.4.5
Summary: Python-ETM Connector
Author-email: Rob Calon <pyetm@pm.me>
License:                       EUROPEAN UNION PUBLIC LICENCE v. 1.2
Project-URL: repository, https://github.com/robcalon/pyetm
Keywords: ETM,Energy Transition Model
Classifier: Development Status :: 4 - Beta
Classifier: Intended Audience :: Developers
Classifier: Intended Audience :: Education
Classifier: Intended Audience :: Science/Research
Classifier: License :: OSI Approved :: European Union Public Licence 1.2 (EUPL 1.2)
Classifier: Natural Language :: English
Classifier: Operating System :: OS Independent
Classifier: Programming Language :: Python
Classifier: Programming Language :: Python :: 3
Classifier: Programming Language :: Python :: 3.10
Classifier: Programming Language :: Python :: 3.11
Classifier: Programming Language :: Python :: 3.12
Requires-Python: >=3.10
License-File: LICENSE
Requires-Dist: requests>=2.26
Requires-Dist: pandas[parquet]>=2.2
Requires-Dist: openpyxl>=3.0
Requires-Dist: xlsxwriter>=3.0
Provides-Extra: async
Requires-Dist: aiohttp>=3.8; extra == "async"
Provides-Extra: dev
Requires-Dist: pre-commit; extra == "dev"
Requires-Dist: pre-commit-hooks; extra == "dev"
Requires-Dist: pytest; extra == "dev"
Requires-Dist: ruff; extra == "dev"
Dynamic: license-file
